renamed_cv2/__init__.py
renamed_cv2/cv2.so
renamed_cv2/libAutoPlugin.so
renamed_cv2/libHeteroPlugin.so
renamed_cv2/libMKLDNNPlugin.so
renamed_cv2/libMultiDevicePlugin.so
renamed_cv2/libavcodec.so
renamed_cv2/libavformat.so
renamed_cv2/libavutil.so
renamed_cv2/libformat_reader.so
renamed_cv2/libfrontend_manager.so
renamed_cv2/libie_backend.so
renamed_cv2/libinference_engine.so
renamed_cv2/libinference_engine_c_api.so
renamed_cv2/libinference_engine_ir_reader.so
renamed_cv2/libinference_engine_ir_v7_reader.so
renamed_cv2/libinference_engine_legacy.so
renamed_cv2/libinference_engine_lp_transformations.so
renamed_cv2/libinference_engine_onnx_reader.so
renamed_cv2/libinference_engine_preproc.so
renamed_cv2/libinference_engine_snippets.so
renamed_cv2/libinference_engine_transformations.so
renamed_cv2/libinterpreter_backend.so
renamed_cv2/libmyriadPlugin.so
renamed_cv2/libngraph.so
renamed_cv2/libngraph_backend.so
renamed_cv2/libonnx_importer.so
renamed_cv2/libonnx_proto.so
renamed_cv2/libprotobuf.so
renamed_cv2/libprotoc.so
renamed_cv2/libswscale.so
renamed_cv2/libtbb.so.2
renamed_cv2/libtemplatePlugin.so
renamed_cv2/libtemplate_extension.so
renamed_cv2/pcie-ma2x8x.mvcmd
renamed_cv2/plugins.xml
renamed_cv2/usb-ma2x8x.mvcmd
renamed_opencv_python_inference_engine-2022.1.5.dist-info/LICENSE
renamed_opencv_python_inference_engine-2022.1.5.dist-info/LICENSE_MIT
renamed_opencv_python_inference_engine-2022.1.5.dist-info/METADATA
renamed_opencv_python_inference_engine-2022.1.5.dist-info/WHEEL
renamed_opencv_python_inference_engine-2022.1.5.dist-info/top_level.txt
renamed_opencv_python_inference_engine-2022.1.5.dist-info/RECORD
